pytest_virtualenv.py
pytest_virtualenv-1.8.1.dist-info/LICENSE
pytest_virtualenv-1.8.1.dist-info/METADATA
pytest_virtualenv-1.8.1.dist-info/WHEEL
pytest_virtualenv-1.8.1.dist-info/entry_points.txt
pytest_virtualenv-1.8.1.dist-info/top_level.txt
pytest_virtualenv-1.8.1.dist-info/RECORD
